tidpy/__init__.py
tidpy/example.py
tidpy-0.0.2.dist-info/LICENSE.txt
tidpy-0.0.2.dist-info/METADATA
tidpy-0.0.2.dist-info/WHEEL
tidpy-0.0.2.dist-info/top_level.txt
tidpy-0.0.2.dist-info/RECORD
