Metadata-Version: 2.1
Name: tidpy
Version: 0.0.2
Summary: Useful code snippets for research and fun.
Home-page: https://github.com/Lzcstan/tidpy.git
Author: Tiding Luo
Author-email: tiding.luo@gmail.com
License: MIT
License-File: LICENSE.txt
